pytorchcrf/__init__.py
pytorchcrf/pytorch_crf.py
pytorchcrf-1.2.0.dist-info/LICENSE
pytorchcrf-1.2.0.dist-info/METADATA
pytorchcrf-1.2.0.dist-info/WHEEL
pytorchcrf-1.2.0.dist-info/top_level.txt
pytorchcrf-1.2.0.dist-info/RECORD
