Metadata-Version: 2.1
Name: pytorchcrf
Version: 1.2.0
Summary: PyTorch CRF with N-best decoding
Home-page: https://github.com/statech/pytorchCRF
Author: Feiyang Niu
Author-email: statech.forums@gmail.com
License: MIT
Keywords: pytorch crf n-best
Platform: UNKNOWN
Classifier: Intended Audience :: Developers
Classifier: Intended Audience :: Science/Research
Classifier: Operating System :: OS Independent
Classifier: License :: OSI Approved :: MIT License
Classifier: Programming Language :: Python :: 3.6
Classifier: Programming Language :: Python :: 3.7
Requires-Python: >=3.6
Requires-Dist: torch
